code_speaks_python/__init__.py
code_speaks_python/core.py
code_speaks_python-0.1.5.dist-info/licenses/LICENSE
code_speaks_python-0.1.5.dist-info/METADATA
code_speaks_python-0.1.5.dist-info/WHEEL
code_speaks_python-0.1.5.dist-info/top_level.txt
code_speaks_python-0.1.5.dist-info/RECORD
