Metadata-Version: 2.4
Name: code_speaks_python
Version: 0.1.5
Summary: Small demo package
Author-email: Naveen <sainaveenadepu@gmail.com>
License: MIT
Project-URL: Homepage, https://github.com/Naveencodespeaks/code_speaks_pypi.git
Project-URL: Bug Tracker, https://github.com/Naveencodespeaks/Python_packages.git/issues
Keywords: example,demo
Classifier: Programming Language :: Python :: 3
Classifier: License :: OSI Approved :: MIT License
Classifier: Operating System :: OS Independent
Requires-Python: >=3.8
License-File: LICENSE
Requires-Dist: requests>=2.0
Dynamic: license-file
